vtds_provider_gcp/__init__.py
vtds_provider_gcp/mock/mock_gcloud/__init__.py
vtds_provider_gcp/mock/mock_terragrunt/__init__.py
vtds_provider_gcp/private/__init__.py
vtds_provider_gcp/private/api_objects.py
vtds_provider_gcp/private/blade_interconnect.py
vtds_provider_gcp/private/common.py
vtds_provider_gcp/private/config.py
vtds_provider_gcp/private/provider.py
vtds_provider_gcp/private/secret_manager.py
vtds_provider_gcp/private/terragrunt.py
vtds_provider_gcp/private/virtual_blade.py
vtds_provider_gcp/private/config/README.md
vtds_provider_gcp/private/config/config.yaml
vtds_provider_gcp/private/config/test_overlay.yaml
vtds_provider_gcp/private/terragrunt/README.md
vtds_provider_gcp/private/terragrunt/framework/README.md
vtds_provider_gcp/private/terragrunt/framework/terragrunt.hcl
vtds_provider_gcp/private/terragrunt/framework/system/README.md
vtds_provider_gcp/private/terragrunt/framework/system/platform/README.md
vtds_provider_gcp/private/terragrunt/framework/system/platform/blade-interconnect/README.md
vtds_provider_gcp/private/terragrunt/framework/system/platform/virtual-blade/README.md
vtds_provider_gcp/private/terragrunt/framework/system/project/deploy/README.md
vtds_provider_gcp/private/terragrunt/framework/system/project/deploy/inputs.yaml
vtds_provider_gcp/private/terragrunt/framework/system/project/deploy/terragrunt.hcl
vtds_provider_gcp/private/terragrunt/templates/README.md
vtds_provider_gcp/private/terragrunt/templates/system/platform/blade-interconnect/README.md
vtds_provider_gcp/private/terragrunt/templates/system/platform/blade-interconnect/firewall/README.md
vtds_provider_gcp/private/terragrunt/templates/system/platform/blade-interconnect/firewall/deploy/inputs.yaml
vtds_provider_gcp/private/terragrunt/templates/system/platform/blade-interconnect/firewall/deploy/terragrunt.hcl
vtds_provider_gcp/private/terragrunt/templates/system/platform/blade-interconnect/routes/README.md
vtds_provider_gcp-0.0.30.dist-info/licenses/LICENSE
vtds_provider_gcp-0.0.30.dist-info/METADATA
vtds_provider_gcp-0.0.30.dist-info/WHEEL
vtds_provider_gcp-0.0.30.dist-info/entry_points.txt
vtds_provider_gcp-0.0.30.dist-info/top_level.txt
vtds_provider_gcp-0.0.30.dist-info/RECORD
